{
    "display": {
        "title": {
            "text": "World VIII | Mini-Overworld",
            "color": "white"
        },
        "description": {
            "text": "In an attempt of returning to normalcy, this world was chosen. The world didn't have much prosperity due to a hostile player environment and lack of background and such.",
            "color": "gray"
        },
        "icon": {
            "item": "minecraft:grass_block"
        },
        "frame": "goal",
        "show_toast": false,
        "announce_to_chat": false,
        "hidden": false
    },
    "criteria": {
        "acquired": {
            "trigger": "minecraft:tick"
        }
    },
    "parent": "slimesurvival:history/world/world_7"
}